chibi_git/__init__.py
chibi_git/branches.py
chibi_git/chibi_git.py
chibi_git/command.py
chibi_git/exception.py
chibi_git/obj.py
chibi_git/snippets.py
chibi_git/tags.py
chibi_git-0.9.1.dist-info/licenses/AUTHORS.rst
chibi_git-0.9.1.dist-info/licenses/LICENSE
chibi_git-0.9.1.dist-info/METADATA
chibi_git-0.9.1.dist-info/WHEEL
chibi_git-0.9.1.dist-info/top_level.txt
chibi_git-0.9.1.dist-info/RECORD
