Metadata-Version: 2.4
Name: chibi_git
Version: 0.9.1
Summary: wrapper to use git in python
Home-page: https://github.com/dem4ply/chibi_git
Author: dem4ply
Author-email: dem4ply@gmail.com
License: WTFPL
Keywords: chibi_git
Classifier: Development Status :: 2 - Pre-Alpha
Classifier: Intended Audience :: Developers
Classifier: License :: Public Domain
Classifier: Natural Language :: English
Classifier: Programming Language :: Python :: 3.7
Classifier: Programming Language :: Python :: 3.8
License-File: LICENSE
License-File: AUTHORS.rst
Requires-Dist: chibi>=0.14.0
Requires-Dist: chibi_atlas>=1.1.0
Requires-Dist: chibi_command>=1.1.2
Dynamic: author
Dynamic: author-email
Dynamic: classifier
Dynamic: description
Dynamic: home-page
Dynamic: keywords
Dynamic: license
Dynamic: license-file
Dynamic: requires-dist
Dynamic: summary
